BBIOPY-0.1.5.dist-info/build/lib/bbiopy/GPIOmay.py
BBIOPY-0.1.5.dist-info/build/lib/bbiopy/PWMmay.py
BBIOPY-0.1.5.dist-info/build/lib/bbiopy/PinMux.py
BBIOPY-0.1.5.dist-info/build/lib/bbiopy/__init__.py
BBIOPY-0.1.5.dist-info/build/lib/bbiopy/adc.py
BBIOPY-0.1.5.dist-info/build/lib/bbiopy/uart.py
bbiopy/GPIOmay.py
bbiopy/PWMmay.py
bbiopy/PinMux.py
bbiopy/__init__.py
bbiopy/adc.py
bbiopy/uart.py
BBIOPY-0.1.5.dist-info/LICENSE
BBIOPY-0.1.5.dist-info/METADATA
BBIOPY-0.1.5.dist-info/WHEEL
BBIOPY-0.1.5.dist-info/top_level.txt
BBIOPY-0.1.5.dist-info/RECORD
