Metadata-Version: 2.1
Name: BBIOPY
Version: 0.1.5
Summary: Full python implementation of BBIO gpiod
Home-page: https://github.com/EricMorse/ECE434-Project
Author: Eric Morse, Joshua Key, and Mark Yoder
Author-email: morsee@rose-hulman.edu
License: UNKNOWN
Platform: UNKNOWN
Classifier: Programming Language :: Python :: 3
Classifier: Operating System :: OS Independent
Requires-Python: >=3.6
